pinnde/__init__.py
pinnde/initials.py
pinnde/adaptives/RAD.py
pinnde/adaptives/RAR.py
pinnde/adaptives/RARD.py
pinnde/adaptives/__init__.py
pinnde/adaptives/adaptives.py
pinnde/boundaries/__init__.py
pinnde/boundaries/boundaries.py
pinnde/boundaries/dirichlet.py
pinnde/boundaries/neumann.py
pinnde/boundaries/odeicbc.py
pinnde/boundaries/periodic.py
pinnde/data/__init__.py
pinnde/data/data.py
pinnde/data/dondata.py
pinnde/data/invpinndata.py
pinnde/data/pinndata.py
pinnde/data/timedondata.py
pinnde/data/timeinvpinndata.py
pinnde/data/timepinndata.py
pinnde/domain/NEllipsoid.py
pinnde/domain/NRect.py
pinnde/domain/Time_NEllipsoid.py
pinnde/domain/Time_NRect.py
pinnde/domain/__init__.py
pinnde/domain/domain.py
pinnde/domain/timedomain.py
pinnde/legacy/__init__.py
pinnde/legacy/ode_Solvers.py
pinnde/legacy/pde_Boundaries_2var.py
pinnde/legacy/pde_Initials.py
pinnde/legacy/pde_Solvers.py
pinnde/legacy/ODE/__init__.py
pinnde/legacy/ODE/ode_ModelFuncs.py
pinnde/legacy/ODE/ode_ParamChecks.py
pinnde/legacy/ODE/ode_Plotters.py
pinnde/legacy/ODE/ode_Points.py
pinnde/legacy/ODE/ode_TimeSteppersDeepONet.py
pinnde/legacy/ODE/ode_trainingSelect.py
pinnde/legacy/ODE/SolveClasses/__init__.py
pinnde/legacy/ODE/SolveClasses/ode_DeepONetSolveClass.py
pinnde/legacy/ODE/SolveClasses/ode_SolveClass.py
pinnde/legacy/ODE/SolveClasses/ode_SystemDeepONetSolveClass.py
pinnde/legacy/ODE/SolveClasses/ode_SystemSolveClass.py
pinnde/legacy/ODE/SpecificTraining/__init__.py
pinnde/legacy/ODE/SpecificTraining/BVP_Training/__init__.py
pinnde/legacy/ODE/SpecificTraining/BVP_Training/ode_TrainingBVP_Hard.py
pinnde/legacy/ODE/SpecificTraining/BVP_Training/ode_TrainingBVP_soft.py
pinnde/legacy/ODE/SpecificTraining/DeepONet_Training/__init__.py
pinnde/legacy/ODE/SpecificTraining/DeepONet_Training/DeepONet_2EquationSystems/__init__.py
pinnde/legacy/ODE/SpecificTraining/DeepONet_Training/DeepONet_2EquationSystems/documentation_TrainingDeepONet_2EquationSystems.py
pinnde-1.2.0.dist-info/licenses/LICENSE.txt
pinnde-1.2.0.dist-info/METADATA
pinnde-1.2.0.dist-info/WHEEL
pinnde-1.2.0.dist-info/top_level.txt
pinnde-1.2.0.dist-info/RECORD
