Metadata-Version: 2.4
Name: pinnde
Version: 1.2.0
Summary: A library for solving differential equations with PINNs and DeepONets
Author-email: Jason Matthews <jbmatthews@mun.ca>
License:                   GNU LESSER GENERAL PUBLIC LICENSE
Classifier: Programming Language :: Python :: 3
Classifier: License :: OSI Approved :: GNU Lesser General Public License v2 (LGPLv2)
Classifier: Topic :: Scientific/Engineering
Classifier: Topic :: Scientific/Engineering :: Artificial Intelligence
Classifier: Topic :: Scientific/Engineering :: Mathematics
Requires-Python: >=3.10.12
License-File: LICENSE.txt
Requires-Dist: tensorflow>=2.18.0
Requires-Dist: tensorflow_probability>=0.25.0
Requires-Dist: tf_keras>=2.18.0
Requires-Dist: numpy
Requires-Dist: pyDOE
Requires-Dist: matplotlib
Requires-Dist: jax>=0.7.0
Requires-Dist: flax>=0.11.1
Requires-Dist: optax>=0.2.2
Dynamic: license-file
